multibacktesting2/__init__.py
multibacktesting2/_plotting.py
multibacktesting2/_stats.py
multibacktesting2/_util.py
multibacktesting2/_version.py
multibacktesting2/autoscale_cb.js
multibacktesting2/backtesting.py
multibacktesting2/lib.py
multibacktesting2/test/EURUSD.csv
multibacktesting2/test/GOOG.csv
multibacktesting2/test/__init__.py
multibacktesting2/test/__main__.py
multibacktesting2/test/_test.py
multibacktesting2-0.1.4.dist-info/LICENSE.md
multibacktesting2-0.1.4.dist-info/METADATA
multibacktesting2-0.1.4.dist-info/WHEEL
multibacktesting2-0.1.4.dist-info/top_level.txt
multibacktesting2-0.1.4.dist-info/RECORD
